{
    "id": "widowmc",
    "name": "Widow Network",
    "store": "https://store.widowmc.net",
    "addresses": [
      "widowmc.net"
    ],
    "primaryAddress": "widowmc.net",
    "primaryColor": "#d50101",
    "secondaryColor": "#FFFFFF",
    "minecraftVersions": [
      "1.19.*",
      "1.20.*",
      "1.21.*"
    ],
    "primaryMinecraftVersion": "1.20.4",
    "primaryRegion": "NA",
    "regions": [
      "NA"
    ],
    "gameTypes": [
      "PvP",
      "Survival"
    ],
    "socials": {
      "discord": "https://discord.gg/widowmc"
    },
    "crossplay": true
  }
